django_haystack_elasticsearch5-0.7.dist-info/DESCRIPTION.rst
django_haystack_elasticsearch5-0.7.dist-info/METADATA
django_haystack_elasticsearch5-0.7.dist-info/RECORD
django_haystack_elasticsearch5-0.7.dist-info/WHEEL
django_haystack_elasticsearch5-0.7.dist-info/metadata.json
django_haystack_elasticsearch5-0.7.dist-info/top_level.txt
haystack_elasticsearch5/__init__.py
haystack_elasticsearch5/backend.py
tests/__init__.py
tests/mocks.py
tests/settings.py
tests/test_backend.py
tests/test_inputs.py
tests/test_query.py
tests/utils.py
tests/test_app/__init__.py
tests/test_app/models.py
tests/test_app/search_indexes.py
tests/test_app/urls.py
tests/test_app/migrations/0001_initial.py
tests/test_app/migrations/__init__.py
