Metadata-Version: 2.0
Name: django-haystack-elasticsearch5
Version: 0.7
Summary: Elasticsearch 5 backend for django-haystack
Home-page: https://github.com/Alkalit/haystack-elasticsearch5
Author: Alexey Kalinin
Author-email: lyoffa412@gmail.com
License: UNKNOWN
Download-URL: https://github.com/Alkalit/haystack-elasticsearch5/tarball/0.7
Keywords: elasticsearch,haystack,search
Platform: UNKNOWN
